taurex_2d/__init__.py
taurex_2d/_version.py
taurex_2d/chemistry.py
taurex_2d/mpi.py
taurex_2d/pressure.py
taurex_2d/taurex.py
taurex_2d/temperature.py
taurex_2d/contributions/__init__.py
taurex_2d/contributions/absorption.py
taurex_2d/contributions/cia.py
taurex_2d/contributions/clouds2D.py
taurex_2d/contributions/contribution.py
taurex_2d/contributions/rayleigh.py
taurex_2d/contributions/simpleclouds.py
taurex_2d/data/__init__.py
taurex_2d/data/profiles/__init__.py
taurex_2d/data/profiles/chemistry/__init__.py
taurex_2d/data/profiles/chemistry/chemistry.py
taurex_2d/data/profiles/chemistry/chemistry2D.py
taurex_2d/data/profiles/chemistry/chemistrymix.py
taurex_2d/data/profiles/chemistry/taurexchemistry.py
taurex_2d/data/profiles/chemistry/gas/__init__.py
taurex_2d/data/profiles/chemistry/gas/constantgas.py
taurex_2d/data/profiles/chemistry/gas/gas.py
taurex_2d/data/profiles/chemistry/gas/gas2D.py
taurex_2d/data/profiles/chemistry/gas/gasratio.py
taurex_2d/data/profiles/pressure/__init__.py
taurex_2d/data/profiles/pressure/pressure2Dprofile.py
taurex_2d/data/profiles/pressure/pressureprofile.py
taurex_2d/data/profiles/temperature/__init__.py
taurex_2d/data/profiles/temperature/file.py
taurex_2d/data/profiles/temperature/guillot.py
taurex_2d/data/profiles/temperature/isothermal.py
taurex_2d/data/profiles/temperature/npoint.py
taurex_2d/data/profiles/temperature/rodgers.py
taurex_2d/data/profiles/temperature/temparray.py
taurex_2d/data/profiles/temperature/temperature2D.py
taurex_2d/data/profiles/temperature/tprofile.py
taurex_2d/data/spectrum/__init__.py
taurex_2d/data/spectrum/array.py
taurex_2d/data/spectrum/iraclis.py
taurex_2d/data/spectrum/lightcurve.py
taurex_2d/data/spectrum/observed.py
taurex_2d/data/spectrum/spectrum.py
taurex_2d/data/spectrum/taurex.py
taurex_2d/data/stellar/__init__.py
taurex_2d/data/stellar/phoenix.py
taurex_2d/data/stellar/star.py
taurex_2d/model/__init__.py
taurex_2d/model/directimage.py
taurex_2d/model/emission.py
taurex_2d-3.1.3b0.dist-info/LICENSE
taurex_2d-3.1.3b0.dist-info/METADATA
taurex_2d-3.1.3b0.dist-info/WHEEL
taurex_2d-3.1.3b0.dist-info/entry_points.txt
taurex_2d-3.1.3b0.dist-info/top_level.txt
taurex_2d-3.1.3b0.dist-info/RECORD
