Metadata-Version: 2.1
Name: taurex-2d
Version: 3.1.3b0
Summary: TauREx 2D plugin
Home-page: https://forge.oasu.u-bordeaux.fr/falco/taurex_2d.git
Author: Aurélien Falco
Author-email: aurelien.falco@u-bordeaux.fr
License: BSD
Keywords: exoplanet,retrieval,taurex,taurex3,taurex2d,atmosphere,atmospheric
Platform: UNKNOWN
Classifier: Development Status :: 4 - Beta
Classifier: Environment :: Console
Classifier: Environment :: Win32 (MS Windows)
Classifier: Intended Audience :: Developers
Classifier: Intended Audience :: Science/Research
Classifier: License :: OSI Approved :: BSD License
Classifier: Operating System :: Microsoft :: Windows
Classifier: Operating System :: POSIX
Classifier: Operating System :: POSIX :: Linux
Classifier: Operating System :: Unix
Classifier: Operating System :: OS Independent
Classifier: Programming Language :: Python :: 3
Classifier: Topic :: Scientific/Engineering
Classifier: Topic :: Software Development :: Libraries
Provides: taurex_2d
License-File: LICENSE
Requires-Dist: taurex
Requires-Dist: numpy
Requires-Dist: numba
Requires-Dist: astropy
Requires-Dist: pandas
Requires-Dist: numexpr
Requires-Dist: tabulate
Provides-Extra: plot
Requires-Dist: matplotlib ; extra == 'plot'
